parallel_conda-0.2.3.dist-info/DESCRIPTION.rst
parallel_conda-0.2.3.dist-info/METADATA
parallel_conda-0.2.3.dist-info/RECORD
parallel_conda-0.2.3.dist-info/WHEEL
parallel_conda-0.2.3.dist-info/entry_points.txt
parallel_conda-0.2.3.dist-info/metadata.json
parallel_conda-0.2.3.dist-info/top_level.txt
parallel_conda-0.2.3.dist-info/zip-safe
pconda/__init__.py
pconda/pconda.py
