Metadata-Version: 2.0
Name: parallel-conda
Version: 0.2.3
Summary: Drop-in parallel replacement for "conda install ..." procedures.
Home-page: https://github.com/milesgranger/parallel-conda
Author: Miles Granger
Author-email: miles.r.granger@gmail.com
License: MIT
Platform: UNKNOWN
Requires-Dist: click (>=6.6)
Requires-Dist: futures
